thzpy/__init__.py
thzpy/_unitchecks.py
thzpy/dotthz/__init__.py
thzpy/frequencydomain/__init__.py
thzpy/frequencydomain/_frequencydomain.py
thzpy/frequencydomain/frequencydomain.py
thzpy/timedomain/__init__.py
thzpy/timedomain/_timedomain.py
thzpy/timedomain/timedomain.py
thzpy/transferfunctions/__init__.py
thzpy/transferfunctions/_transferfunctions.py
thzpy/transferfunctions/_transmission.py
thzpy/transferfunctions/transferfunctions.py
thzpy-0.2.1.dist-info/licenses/LICENSE
thzpy-0.2.1.dist-info/METADATA
thzpy-0.2.1.dist-info/WHEEL
thzpy-0.2.1.dist-info/top_level.txt
thzpy-0.2.1.dist-info/RECORD
