Metadata-Version: 2.4
Name: thzpy
Version: 0.2.1
Summary: Data proccessing for THz-TDS. A scientific computing package for the processing of terahertz time-domain spectroscopy data. Includes modules for time-domain, transfer functions, frequency-domain, and data formatting.
Author-email: Jasper Ward-Berry <jnw35@cam.ac.uk>
Project-URL: Homepage, https://github.com/dotTHzTAG/thzpy
Project-URL: Bug Tracker, https://github.com/dotTHzTAG/thzpy/issues
Classifier: Development Status :: 3 - Alpha
Classifier: Intended Audience :: Science/Research
Classifier: Programming Language :: Python :: 3
Classifier: Operating System :: Microsoft :: Windows
Requires-Python: >=3.7
License-File: LICENSE
Requires-Dist: numpy
Requires-Dist: pydotthz>=1.0.1
Dynamic: license-file
